MANIFEST.in
README.txt
setup.cfg
setup.py
docs/HISTORY.txt
docs/INSTALL.txt
docs/LICENSE.GPL
docs/LICENSE.txt
ploomcake/__init__.py
ploomcake/__init__.pyc
ploomcake.theme_collection_accessibility.egg-info/PKG-INFO
ploomcake.theme_collection_accessibility.egg-info/SOURCES.txt
ploomcake.theme_collection_accessibility.egg-info/dependency_links.txt
ploomcake.theme_collection_accessibility.egg-info/entry_points.txt
ploomcake.theme_collection_accessibility.egg-info/namespace_packages.txt
ploomcake.theme_collection_accessibility.egg-info/not-zip-safe
ploomcake.theme_collection_accessibility.egg-info/requires.txt
ploomcake.theme_collection_accessibility.egg-info/top_level.txt
ploomcake/theme_collection_accessibility/__init__.py
ploomcake/theme_collection_accessibility/configure.zcml
ploomcake/theme_collection_accessibility/tests.py
ploomcake/theme_collection_accessibility/browser/__init__.py
ploomcake/theme_collection_accessibility/browser/baseoption.py
ploomcake/theme_collection_accessibility/browser/configure.zcml
ploomcake/theme_collection_accessibility/browser/bigfonts/__init__.py
ploomcake/theme_collection_accessibility/browser/bigfonts/configure.zcml
ploomcake/theme_collection_accessibility/browser/bigfonts/option.py
ploomcake/theme_collection_accessibility/browser/bigfonts/resources/preview.png
ploomcake/theme_collection_accessibility/browser/bigfonts/resources/style.css
ploomcake/theme_collection_accessibility/browser/highcontrast/__init__.py
ploomcake/theme_collection_accessibility/browser/highcontrast/configure.zcml
ploomcake/theme_collection_accessibility/browser/highcontrast/option.py
ploomcake/theme_collection_accessibility/browser/highcontrast/resources/preview.png
ploomcake/theme_collection_accessibility/browser/highcontrast/resources/style.css
ploomcake/theme_collection_accessibility/profiles/default/cssregistry.xml
ploomcake/theme_collection_accessibility/profiles/default/metadata.xml