Metadata-Version: 1.0
Name: ploomcake.theme-collection-accessibility
Version: 0.1
Summary: A collection of Ploomcake addictional styles designed for partially sighted people
Home-page: https://github.com/ploomcake/ploomcake.theme_collection_accessibility
Author: Maurizio Lupo
Author-email: maurizio.lupo@redomino.com
License: GPL
Platform: UNKNOWN
Classifier: Framework :: Plone
Classifier: Programming Language :: Python
